<?xml version="1.0" encoding="utf-8"?>
<RoadParams xmlns:xsi="http://www.w3.org/2001/XMLSchema-instance" xmlns:xsd="http://www.w3.org/2001/XMLSchema">
  <LengthRatio>1</LengthRatio>
  <WidthRatio>1</WidthRatio>
  <Tile>10</Tile>
  <TileFluctuation>true</TileFluctuation>
  <TileFluctuationWidth>4</TileFluctuationWidth>
  <TileFluctuationSmooth>0.5</TileFluctuationSmooth>
  <Height>-1</Height>
  <HeightFadeWidth>4</HeightFadeWidth>
  <HeightFadeSmooth>0.5</HeightFadeSmooth>
  <ClipByHills>false</ClipByHills>
  <ClipByHoles>false</ClipByHoles>
  <Group />
  <Stripes>
    <RoadStripe>
      <Anchor>Center</Anchor>
      <Side>Both</Side>
      <Shift>0</Shift>
      <Tile>31</Tile>
      <TileWidth>4</TileWidth>
      <TileFluctuation>true</TileFluctuation>
      <TileFluctuationWidth>2</TileFluctuationWidth>
      <TileFluctuationSmooth>0.5</TileFluctuationSmooth>
      <Height>1</Height>
      <HeightWidth>4</HeightWidth>
      <HeightFadeWidth>2</HeightFadeWidth>
      <HeightFadeSmooth>0.5</HeightFadeSmooth>
      <Name>RoadStripe</Name>
    </RoadStripe>
  </Stripes>
  <ItemSets>
    <RoadItemSet>
      <Anchor>Edge</Anchor>
      <Side>Both</Side>
      <DistanceType>Absolute</DistanceType>
      <AlignType>PreviousItemFlipped</AlignType>
      <Shift>2</Shift>
      <MinDistance>8.5</MinDistance>
      <MaxDistance>8.5</MaxDistance>
      <Probability>1</Probability>
      <PositionFluctuation>1</PositionFluctuation>
      <RotationFluctuation>0</RotationFluctuation>
      <ScaleFluctuation>0</ScaleFluctuation>
      <Group>Fence</Group>
      <Name>RoadItemSet</Name>
      <Items>
        <Items>
          <WeightItemOfString>
            <Item>World/Races/Kania/Environment/Models/Hedge/K_Fence_01.(StaticObject).xdb</Item>
            <Weight>1</Weight>
            <Name>WeightItem</Name>
          </WeightItemOfString>
          <WeightItemOfString>
            <Item>World/Races/Kania/Environment/Models/Fence/K_Fence_02.(StaticObject).xdb</Item>
            <Weight>1</Weight>
            <Name>WeightItem</Name>
          </WeightItemOfString>
          <WeightItemOfString>
            <Item>World/Races/Kania/Environment/Models/Fence/K_Fence_03.(StaticObject).xdb</Item>
            <Weight>1</Weight>
            <Name>WeightItem</Name>
          </WeightItemOfString>
        </Items>
      </Items>
    </RoadItemSet>
  </ItemSets>
</RoadParams>